{
  "AWSTemplateFormatVersion" : "2010-09-09",
  "Description" : "AWS CloudFormation Sample Template glusterfs-ephemeral.template: Sample template that creates X number of Y TB GlusterFS nodes.",
  "Parameters" : {
    "KeyName" : {
      "Description" : "Name of an existing EC2 KeyPair to enable SSH access to the instances",
      "Type" : "String",
      "MinLength" : "1",
      "MaxLength" : "64",
      "AllowedPattern" : "[-_ a-zA-Z0-9]*",
      "ConstraintDescription" : "can contain only alphanumeric characters, spaces, dashes and underscores."
    },
    "AccessFrom" : {
      "Description" : "Lockdown access to Gluster services (default is accessiable for 0.0.0.0/0)",
      "Type" : "String",
      "MinLength" : "9",
      "MaxLength" : "18",
      "Default" : "0.0.0.0/0",
      "AllowedPattern" : "(\\d{1,3})\\.(\\d{1,3})\\.(\\d{1,3})\\.(\\d{1,3})/(\\d{1,2})",
      "ConstraintDescription" : "must be a valid CIDR range of the form x.x.x.x/x."
    },
    "GlusterInstanceType" : {
      "Description" : "Backend Server EC2 instance type",
      "Type" : "String",
      "Default" : "m3.xlarge",
      "AllowedValues" : [
        "t1.micro",
        "m1.small",
        "m1.medium",
        "m1.large",
        "m1.xlarge",
        "m2.xlarge",
        "m2.2xlarge",
        "m2.4xlarge",
        "c1.medium",
        "c1.xlarge",
        "cc1.4xlarge",
        "cc2.8xlarge",
        "hi1.4xlarge",
        "m3.xlarge",
        "m3.2xlarge",
         "hs1.8xlarge"
      ],
      "ConstraintDescription" : "must be a valid EC2 instance type."
    },
    "ClusterSize" : {
      "Description" : "Number of EC2 instances to launch for the backend server",
      "Type" : "Number",
      "Default" : "2",
      "AllowedValues" : [
      	"1",
        "2",
        "4",
        "6",
        "8",
        "10",
        "12",
        "14",
        "16"
      ]
    },
    "Encryption" : {
      "Description" : "Indicate Block Level Encryption required (encrypt or DoNotEncrypt )",
      "Type" : "String",
      "Default" : "encrypt",
      "AllowedValues" : [
        "encrypt",
        "DoNotEncrypt"
      ]
    },
    "VpcSubnetId" : {
      "Description" : "Id of an exisiting VPC subnet i.e. subnet-ae4ebec4",
      "Type" : "String",
      "Default" : "subnet-d904ddae",
      "MinLength" : "1",
      "MaxLength" : "64",
      "AllowedPattern" : "subnet-[a-z0-9]*",
      "ConstraintDescription" : "can contain only alphanumeric characters, spaces, dashes and underscores."
    },
    "VpcId" : {
      "Description" : "Id of an exisiting VPC that contains the subnet defined in VpcSubnetId i.e. vpc-d54ebebf",
      "Type" : "String",
      "MinLength" : "1",
      "MaxLength" : "64",
      "AllowedPattern" : "vpc-[a-z0-9]*",
      "ConstraintDescription" : "can contain only alphanumeric characters, spaces, dashes and underscores.",
      "Default" : "vpc-46e35823"
    },
    "SubnetAZ" : {
      "Description" : "Availability Zone of the subnet specified by VpcSubnetId",
      "Type" : "String",
      "MinLength" : "1",
      "MaxLength" : "64",
      "ConstraintDescription" : "can contain only alphanumeric characters, spaces, dashes and underscores.",
      "AllowedPattern" : "[-_ a-zA-Z0-9]*",
      "Default" : "us-east-1c"
    },
    "FSType" : {
      "Description" : "Filesystem type i.e. distributed or replicated-2",
      "Type" : "String",
      "Default" : "replicated-2",
      "ConstraintDescription" : "Must match one of the supported GlusterFS filesystem types"
    }
  },
  "Mappings" : {
    "AWSInstanceType2Arch" : {
      "t1.micro" : {
        "Arch" : "64"
      },
      "m1.small" : {
        "Arch" : "64"
      },
      "m1.medium" : {
        "Arch" : "64"
      },
      "m1.large" : {
        "Arch" : "64"
      },
      "m1.xlarge" : {
        "Arch" : "64"
      },
      "m2.xlarge" : {
        "Arch" : "64"
      },
      "m2.2xlarge" : {
        "Arch" : "64"
      },
      "m2.4xlarge" : {
        "Arch" : "64"
      },
      "c1.medium" : {
        "Arch" : "64"
      },
      "c1.xlarge" : {
        "Arch" : "64"
      },
      "cc1.4xlarge" : {
        "Arch" : "64Cluster"
      },
      "cc2.8xlarge" : {
        "Arch" : "64Cluster"
      },
      "hs1.8xlarge" : {
        "Arch" : "64Cluster"
      },
      "m3.xlarge" : {
        "Arch" : "64"
      },
      "m3.2xlarge" : {
        "Arch" : "64"
      }
    },
    "AWSRegionArch2AMI" : {
      "us-east-1" : {
        "64" : "ami-1624987f",
        "64Cluster" : "ami-08249861"
      },
      "us-west-2" : {
        "64" : "ami-2a31bf1a",
        "64Cluster" : "ami-2431bf14"
      },
      "eu-west-1" : {
        "64" : "ami-c37474b7",
        "64Cluster" : "ami-d97474ad"
      },
      "us-west-1" : {
        "64" : "ami-1bf9de5e",
        "64Cluster" : "NOT_YET_SUPPORTED"
      },
      "ap-southeast-1" : {
        "64" : "ami-a6a7e7f4",
        "64Cluster" : "NOT_YET_SUPPORTED"
      },
      "ap-northeast-1" : {
        "64" : "ami-4e6cd34f",
        "64Cluster" : "NOT_YET_SUPPORTED"
      },
      "ap-southeast-2" : {
        "64" : "ami-bd990e87",
        "64Cluster" : "NOT_YET_SUPPORTED"
      },
      "sa-east-1" : {
        "64" : "ami-1e08d103",
        "64Cluster" : "NOT_YET_SUPPORTED"
      }
    }
  },
  "Resources" : {
    "GlusterFleet" : {
      "Type" : "AWS::AutoScaling::AutoScalingGroup",
      "Properties" : {
        "LaunchConfigurationName" : {
          "Ref" : "GlusterLaunchConfig"
        },
        "DesiredCapacity" : {
          "Ref" : "ClusterSize"
        },
        "Tags" : [
          {
            "Key" : "tag",
            "Value" : "glusterfs",
            "PropagateAtLaunch" : "true"
          }
        ],
        "MaxSize" : {
          "Ref" : "ClusterSize"
        },
        "MinSize" : {
          "Ref" : "ClusterSize"
        },
        "VPCZoneIdentifier" : [
          {
            "Ref" : "VpcSubnetId"
          }
        ],
        "AvailabilityZones" : [
          {
            "Ref" : "SubnetAZ"
          }
        ]
      },
      "DependsOn" : "GlusterSecurityGroupIngress"
    },
    "GlusterLaunchConfig" : {
      "Type" : "AWS::AutoScaling::LaunchConfiguration",
      "Metadata" : {
        "AWS::CloudFormation::Init" : {
          "config" : {
            "packages" : {
              "yum" : {
                "xfsprogs" : [],
                "postfix" : [],
                "parted" : [],
                "nfs-utils" : []
              }
            },
            "services" : {
              "sysvinit" : {
                "postfix" : {
                  "enabled" : "true",
                  "ensureRunning" : "true"
                },
                "sendmail" : {
                  "enabled" : "false",
                  "ensureRunning" : "false"
                },
                "rpcbind" : {
                  "enabled" : "true",
                  "ensureRunning" : "true"
                }
              }
            },
            "files" : {
              "/etc/cfn/bash.env" : {
                "content" : {
                  "Fn::Join" : [
                    "",
                    [
                      "cfn_stack_name=",
                      {
                        "Ref" : "AWS::StackName"
                      },
                      "\n",
                      "cfn_instances=",
                      {
                        "Ref" : "ClusterSize"
                      },
                      "\n",
                      "cfn_fs_type=",
                      {
                        "Ref" : "FSType"
                      },
                      "\n",
                      "cfn_region=",
                      {
                        "Ref" : "AWS::Region"
                      },
                      "\n"
                    ]
                  ]
                },
                "mode" : "000400",
                "owner" : "root",
                "group" : "root"
              },
              "/usr/local/sbin/tcp-tuning.sh" : {
                "mode" : "000700",
                "owner" : "root",
                "group" : "root",
                "source" : "https://s3.amazonaws.com/rdi-devops/Scripts/GlusterFS/tcp-tuning.sh"
              },
              "/root/cfn-setup-gluster.sh" : {
                "mode" : "000700",
                "owner" : "root",
                "group" : "root",
                "source" : "https://s3.amazonaws.com/rdi-devops/Scripts/GlusterFS/cfn-setup-gluster.sh"
              }
            }
          }
        }
      },
      "Properties" : {
        "AssociatePublicIpAddress" : "true",
        "ImageId" : {
          "Fn::FindInMap" : [
            "AWSRegionArch2AMI",
            {
              "Ref" : "AWS::Region"
            },
            {
              "Fn::FindInMap" : [
                "AWSInstanceType2Arch",
                {
                  "Ref" : "GlusterInstanceType"
                },
                "Arch"
              ]
            }
          ]
        },
        "SecurityGroups" : [
          {
            "Ref" : "GlusterSecurityGroup"
          }
        ],
        "InstanceType" : {
          "Ref" : "GlusterInstanceType"
        },
        "KeyName" : {
          "Ref" : "KeyName"
        },
        "BlockDeviceMappings" : [
          {
            "DeviceName" : "/dev/sdb",
            "VirtualName" : "ephemeral0"
          },
          {
            "DeviceName" : "/dev/sdc",
            "VirtualName" : "ephemeral1"
          },
          {
            "DeviceName" : "/dev/sdd",
            "VirtualName" : "ephemeral2"
          },
          {
            "DeviceName" : "/dev/sde",
            "VirtualName" : "ephemeral3"
          },
          {
            "DeviceName" : "/dev/sdf",
            "VirtualName" : "ephemeral4"
          },
          {
            "DeviceName" : "/dev/sdg",
            "VirtualName" : "ephemeral5"
          },
          {
            "DeviceName" : "/dev/sdh",
            "VirtualName" : "ephemeral6"
          },
          {
            "DeviceName" : "/dev/sdi",
            "VirtualName" : "ephemeral7"
          },
          {
            "DeviceName" : "/dev/sdj",
            "VirtualName" : "ephemeral8"
          },
          {
            "DeviceName" : "/dev/sdk",
            "VirtualName" : "ephemeral9"
          },
          {
            "DeviceName" : "/dev/sdl",
            "VirtualName" : "ephemeral10"
          },
          {
            "DeviceName" : "/dev/sdm",
            "VirtualName" : "ephemeral11"
          },
          {
            "DeviceName" : "/dev/sdn",
            "VirtualName" : "ephemeral12"
          },
          {
            "DeviceName" : "/dev/sdo",
            "VirtualName" : "ephemeral13"
          },
          {
            "DeviceName" : "/dev/sdp",
            "VirtualName" : "ephemeral14"
          },
          {
            "DeviceName" : "/dev/sdq",
            "VirtualName" : "ephemeral15"
          },
          {
            "DeviceName" : "/dev/sdr",
            "VirtualName" : "ephemeral16"
          },
          {
            "DeviceName" : "/dev/sds",
            "VirtualName" : "ephemeral17"
          },
          {
            "DeviceName" : "/dev/sdt",
            "VirtualName" : "ephemeral18"
          },
          {
            "DeviceName" : "/dev/sdu",
            "VirtualName" : "ephemeral19"
          },
          {
            "DeviceName" : "/dev/sdv",
            "VirtualName" : "ephemeral20"
          },
          {
            "DeviceName" : "/dev/sdw",
            "VirtualName" : "ephemeral21"
          },
          {
            "DeviceName" : "/dev/sdx",
            "VirtualName" : "ephemeral22"
          },
          {
            "DeviceName" : "/dev/sdy",
            "VirtualName" : "ephemeral23"
          }
        ],
        "IamInstanceProfile" : {
          "Ref" : "RootInstanceProfile"
        },
        "UserData" : {
          "Fn::Base64" : {
            "Fn::Join" : [
              "",
              [
                "Content-Type: multipart/mixed; boundary=\"===============8288250434371035958==\"\n",
                "MIME-Version: 1.0\n",
                "\n",
                "--===============8288250434371035958==\n",
                "Content-Type: text/cloud-config; charset=\"us-ascii\"\n",
                "MIME-Version: 1.0\n",
                "Content-Transfer-Encoding: 7bit\n",
                "Content-Disposition: attachment; filename=\"cloud-config.txt\"\n",
                "\n",
                "#cloud-config\n",
                "mounts:\n",
                " - [ ephemeral0, none, none ]\n",
                " - [ ephemeral1, none, none ]\n",
                " - [ ephemeral2, none, none ]\n",
                " - [ ephemeral3, none, none ]\n",
                "\n",
                "--===============8288250434371035958==\n",
                "Content-Type: text/x-shellscript; charset=\"us-ascii\"\n",
                "MIME-Version: 1.0\n",
                "Content-Transfer-Encoding: 7bit\n",
                "Content-Disposition: attachment; filename=\"setup.sh\"\n",
                "\n",
                "#!/bin/bash -v\n",
                "yum update -y aws-cfn-bootstrap\n",
                "# Run cfn-init\n",
                "/opt/aws/bin/cfn-init --stack ",
                {
                  "Ref" : "AWS::StackName"
                },
                " --resource GlusterLaunchConfig ",
                "    --region ",
                {
                  "Ref" : "AWS::Region"
                },
                "\n",
                "# Enable network tuning\n",
                "echo -e \"/usr/local/sbin/tcp-tuning.sh\\n\" >> /etc/rc.local\n",
                "# Setup Gluster\n",
                "/root/cfn-setup-gluster.sh ", {"Ref" : "Encryption"}," > /root/gluster-setup.log 2>&1\n",
                "# Signal completion\n",
                "/opt/aws/bin/cfn-signal -e $? -r \"Gluster setup done\" '",
                {
                  "Ref" : "GlusterWaitHandle"
                },
                "'\n",
                "\n",
                "--===============8288250434371035958=="
              ]
            ]
          }
        }
      }
    },
    "GlusterSecurityGroup" : {
      "Type" : "AWS::EC2::SecurityGroup",
      "Properties" : {
        "GroupDescription" : "Subnet access to GlusterFS servers",
        "SecurityGroupIngress" : [
          {
            "IpProtocol" : "tcp",
            "FromPort" : "22",
            "ToPort" : "22",
            "CidrIp" : {
              "Ref" : "AccessFrom"
            }
          },
          {
            "IpProtocol" : "tcp",
            "FromPort" : "24007",
            "ToPort" : "24047",
            "CidrIp" : {
              "Ref" : "AccessFrom"
            }
          },
          {
            "IpProtocol" : "tcp",
            "FromPort" : "111",
            "ToPort" : "111",
            "CidrIp" : {
              "Ref" : "AccessFrom"
            }
          },
          {
            "IpProtocol" : "udp",
            "FromPort" : "111",
            "ToPort" : "111",
            "CidrIp" : {
              "Ref" : "AccessFrom"
            }
          },                
          {
            "IpProtocol" : "tcp",
            "FromPort" : "38465",
            "ToPort" : "38468",
            "CidrIp" : {
              "Ref" : "AccessFrom"
            }
          }
        ],
        "VpcId" : {
          "Ref" : "VpcId"
        }
      }
    },
    "GlusterWaitHandle" : {
      "Type" : "AWS::CloudFormation::WaitConditionHandle"
    },
    "GlusterWaitCondition" : {
      "Type" : "AWS::CloudFormation::WaitCondition",
      "DependsOn" : "GlusterFleet",
      "Properties" : {
        "Handle" : {
          "Ref" : "GlusterWaitHandle"
        },
        "Timeout" : "600",
        "Count" : {
          "Ref" : "ClusterSize"
        }
      }
    },
    "CfnUser" : {
      "Type" : "AWS::IAM::User",
      "Properties" : {
        "Path" : "/",
        "Policies" : [
          {
            "PolicyName" : "root",
            "PolicyDocument" : {
              "Statement" : [
                {
                  "Effect" : "Allow",
                  "Action" : "cloudformation:DescribeStackResource",
                  "Resource" : "*"
                },
                {
                  "Action" : "cloudwatch:PutMetricData",
                  "Effect" : "Allow",
                  "Resource" : "*"
                }
              ]
            }
          }
        ]
      }
    },
    "RootRole" : {
      "Type" : "AWS::IAM::Role",
      "Properties" : {
        "AssumeRolePolicyDocument" : {
          "Statement" : [
            {
              "Effect" : "Allow",
              "Principal" : {
                "Service" : [
                  "ec2.amazonaws.com"
                ]
              },
              "Action" : [
                "sts:AssumeRole"
              ]
            }
          ]
        },
        "Path" : "/"
      }
    },
    "RolePolicies" : {
      "Type" : "AWS::IAM::Policy",
      "Properties" : {
        "PolicyName" : "root",
        "PolicyDocument" : {
          "Statement" : [
            {
              "Effect" : "Allow",
              "Resource" : "*",
              "Action" : [
                "EC2:DescribeInstances",
                "EC2:DescribeInstanceStatus",
                "EC2:DescribeNetworkInterfaces",
                "EC2:DescribeTags",
                "EC2:CreateTags"
              ]
            }
          ]
        },
        "Roles" : [
          {
            "Ref" : "RootRole"
          }
        ]
      }
    },
    "RootInstanceProfile" : {
      "Type" : "AWS::IAM::InstanceProfile",
      "Properties" : {
        "Path" : "/",
        "Roles" : [
          {
            "Ref" : "RootRole"
          }
        ]
      }
    },
    "HostKeys" : {
      "Type" : "AWS::IAM::AccessKey",
      "Properties" : {
        "UserName" : {
          "Ref" : "CfnUser"
        }
      }
    },
    "GlusterSecurityGroupIngress" : {
      "Type" : "AWS::EC2::SecurityGroupIngress",
      "Properties" : {
        "IpProtocol" : "-1",
        "FromPort" : "0",
        "ToPort" : "65535",
        "SourceSecurityGroupId" : {
          "Ref" : "GlusterSecurityGroup"
        },
        "GroupId" : {
          "Ref" : "GlusterSecurityGroup"
        }
      },
      "DependsOn" : "GlusterSecurityGroup"
    }   
  },
  "Outputs":{  
      "HowToMountVolume":{  
         "Value": "How to mount a client",
         "Description":"Before mount, you should associate GlusterClientSecurityGroup with client instances.\n for manual operation use : sudo mount  -t nfs -o nolock NASHeadIP:/glusterfs YourMountPoint"
      }
   }  
}